okta/__init__.py
okta/api_client.py
okta/api_response.py
okta/call_info.py
okta/client.py
okta/configuration.py
okta/constants.py
okta/error_messages.py
okta/exceptions.py
okta/http_client.py
okta/jwt.py
okta/logger.py
okta/oauth.py
okta/okta_collection.py
okta/okta_configuration.py
okta/okta_object.py
okta/pagination.py
okta/py.typed
okta/request_executor.py
okta/rest.py
okta/user_agent.py
okta/utils.py
okta/api/__init__.py
okta/api/agent_pools_api.py
okta/api/api_service_integrations_api.py
okta/api/api_token_api.py
okta/api/application_api.py
okta/api/application_connections_api.py
okta/api/application_cross_app_access_connections_api.py
okta/api/application_features_api.py
okta/api/application_grants_api.py
okta/api/application_groups_api.py
okta/api/application_logos_api.py
okta/api/application_policies_api.py
okta/api/application_sso_api.py
okta/api/application_sso_credential_key_api.py
okta/api/application_sso_federated_claims_api.py
okta/api/application_sso_public_keys_api.py
okta/api/application_tokens_api.py
okta/api/application_users_api.py
okta/api/associated_domain_customizations_api.py
okta/api/attack_protection_api.py
okta/api/authenticator_api.py
okta/api/authorization_server_api.py
okta/api/authorization_server_assoc_api.py
okta/api/authorization_server_claims_api.py
okta/api/authorization_server_clients_api.py
okta/api/authorization_server_keys_api.py
okta/api/authorization_server_policies_api.py
okta/api/authorization_server_rules_api.py
okta/api/authorization_server_scopes_api.py
okta/api/behavior_api.py
okta/api/brands_api.py
okta/api/captcha_api.py
okta/api/custom_domain_api.py
okta/api/custom_pages_api.py
okta/api/custom_templates_api.py
okta/api/device_api.py
okta/api/device_assurance_api.py
okta/api/device_integrations_api.py
okta/api/device_posture_check_api.py
okta/api/directories_integration_api.py
okta/api/email_customization_api.py
okta/api/email_domain_api.py
okta/api/email_server_api.py
okta/api/event_hook_api.py
okta-3.1.0.dist-info/licenses/LICENSE.md
okta-3.1.0.dist-info/METADATA
okta-3.1.0.dist-info/WHEEL
okta-3.1.0.dist-info/top_level.txt
okta-3.1.0.dist-info/RECORD
